<?xml version="1.0"?>
<nfeProc xmlns="http://www.portalfiscal.inf.br/nfe" versao="4.00">
  <NFe xmlns="http://www.portalfiscal.inf.br/nfe">
    <infNFe Id="NFe33607102110230600010107517765640727607020031" versao="4.00">
      <ide>
        <cUF>27</cUF>
        <cNF>cNF</cNF>
        <natOp>Venda de Mercadorias</natOp>
        <mod>65</mod>
        <serie>serie</serie>
        <nNF>nNF</nNF>
        <dhEmi>2022-01-09T10:39:52-03:00</dhEmi>
        <tpNF>1</tpNF>
        <idDest>1</idDest>
        <cMunFG>2700300</cMunFG>
        <tpImp>4</tpImp>
        <tpEmis>1</tpEmis>
        <cDV>cDV</cDV>
        <tpAmb>1</tpAmb>
        <finNFe>1</finNFe>
        <indFinal>1</indFinal>
        <indPres>1</indPres>
        <procEmi>0</procEmi>
        <verProc>3.01.18</verProc>
      </ide>
      <emit>
        <CNPJ>10704071177600</CNPJ>
        <xNome>xNome</xNome>
        <xFant>xFant</xFant>
        <enderEmit>
          <xLgr>xLgr</xLgr>
          <nro>nro</nro>
          <xBairro>xBairro</xBairro>
          <cMun>cMun</cMun>
          <xMun>xMun</xMun>
          <UF>UF</UF>
          <CEP>CEP</CEP>
          <cPais>1058</cPais>
          <xPais>Brasil</xPais>
          <fone>fone</fone>
        </enderEmit>
        <IE>IE</IE>
        <CRT>CRT</CRT>
      </emit>
      <det nItem="1">
        <prod>
          <cProd>48884</cProd>
          <cEAN>7896005030073</cEAN>
          <xProd>Bisc Pilar Coquinho</xProd>
          <NCM>19053100</NCM>
          <CFOP>5405</CFOP>
          <uCom>UN</uCom>
          <qCom>1.0000</qCom>
          <vUnCom>4.1300000000</vUnCom>
          <vProd>4.13</vProd>
          <cEANTrib>7896005030073</cEANTrib>
          <uTrib>UN</uTrib>
          <qTrib>1.0000</qTrib>
          <vUnTrib>4.1300000000</vUnTrib>
          <indTot>1</indTot>
        </prod>
        <imposto>
          <vTotTrib>0.00</vTotTrib>
          <ICMS>
            <ICMS60>
              <orig>0</orig>
              <CST>60</CST>
              <pRedBCEfet>0.00</pRedBCEfet>
              <vBCEfet>4.13</vBCEfet>
              <pICMSEfet>0.00</pICMSEfet>
              <vICMSEfet>0.00</vICMSEfet>
            </ICMS60>
          </ICMS>
          <PIS>
            <PISAliq>
              <CST>01</CST>
              <vBC>4.13</vBC>
              <pPIS>1.65</pPIS>
              <vPIS>0.07</vPIS>
            </PISAliq>
          </PIS>
          <COFINS>
            <COFINSAliq>
              <CST>01</CST>
              <vBC>4.13</vBC>
              <pCOFINS>7.60</pCOFINS>
              <vCOFINS>0.31</vCOFINS>
            </COFINSAliq>
          </COFINS>
        </imposto>
      </det>
      <det nItem="2">
        <prod>
          <cProd>47617</cProd>
          <cEAN>7896016441042</cEAN>
          <xProd>Bisc Pajucara Afa Ch</xProd>
          <NCM>19053100</NCM>
          <CEST>1705300</CEST>
          <CFOP>5405</CFOP>
          <uCom>UN</uCom>
          <qCom>1.0000</qCom>
          <vUnCom>3.5900000000</vUnCom>
          <vProd>3.59</vProd>
          <cEANTrib>7896016441042</cEANTrib>
          <uTrib>UN</uTrib>
          <qTrib>1.0000</qTrib>
          <vUnTrib>3.5900000000</vUnTrib>
          <indTot>1</indTot>
        </prod>
        <imposto>
          <vTotTrib>0.00</vTotTrib>
          <ICMS>
            <ICMS60>
              <orig>0</orig>
              <CST>60</CST>
              <pRedBCEfet>0.00</pRedBCEfet>
              <vBCEfet>3.59</vBCEfet>
              <pICMSEfet>0.00</pICMSEfet>
              <vICMSEfet>0.00</vICMSEfet>
            </ICMS60>
          </ICMS>
          <PIS>
            <PISOutr>
              <CST>49</CST>
              <vBC>3.59</vBC>
              <pPIS>0</pPIS>
              <vPIS>0</vPIS>
            </PISOutr>
          </PIS>
          <COFINS>
            <COFINSOutr>
              <CST>49</CST>
              <vBC>3.59</vBC>
              <pCOFINS>0</pCOFINS>
              <vCOFINS>0</vCOFINS>
            </COFINSOutr>
          </COFINS>
        </imposto>
      </det>
      <det nItem="3">
        <prod>
          <cProd>46593</cProd>
          <cEAN>7896005232705</cEAN>
          <xProd>Far De Trigo D. Bent</xProd>
          <NCM>11010010</NCM>
          <CEST>1704418</CEST>
          <CFOP>5405</CFOP>
          <uCom>UN</uCom>
          <qCom>1.0000</qCom>
          <vUnCom>5.1900000000</vUnCom>
          <vProd>5.19</vProd>
          <cEANTrib>7896005232705</cEANTrib>
          <uTrib>UN</uTrib>
          <qTrib>1.0000</qTrib>
          <vUnTrib>5.1900000000</vUnTrib>
          <indTot>1</indTot>
        </prod>
        <imposto>
          <vTotTrib>0.00</vTotTrib>
          <ICMS>
            <ICMS60>
              <orig>0</orig>
              <CST>60</CST>
              <pRedBCEfet>0.00</pRedBCEfet>
              <vBCEfet>5.19</vBCEfet>
              <pICMSEfet>0.00</pICMSEfet>
              <vICMSEfet>0.00</vICMSEfet>
            </ICMS60>
          </ICMS>
          <PIS>
            <PISNT>
              <CST>06</CST>
            </PISNT>
          </PIS>
          <COFINS>
            <COFINSNT>
              <CST>06</CST>
            </COFINSNT>
          </COFINS>
        </imposto>
      </det>
      <det nItem="4">
        <prod>
          <cProd>45878</cProd>
          <cEAN>7896481120039</cEAN>
          <xProd>Cafe Em Po Kent 250g</xProd>
          <NCM>09012100</NCM>
          <CEST>1709600</CEST>
          <CFOP>5405</CFOP>
          <uCom>UN</uCom>
          <qCom>3.0000</qCom>
          <vUnCom>6.6900000000</vUnCom>
          <vProd>20.07</vProd>
          <cEANTrib>7896481120039</cEANTrib>
          <uTrib>UN</uTrib>
          <qTrib>3.0000</qTrib>
          <vUnTrib>6.6900000000</vUnTrib>
          <indTot>1</indTot>
        </prod>
        <imposto>
          <vTotTrib>0.00</vTotTrib>
          <ICMS>
            <ICMS60>
              <orig>0</orig>
              <CST>60</CST>
              <pRedBCEfet>0.00</pRedBCEfet>
              <vBCEfet>20.07</vBCEfet>
              <pICMSEfet>0.00</pICMSEfet>
              <vICMSEfet>0.00</vICMSEfet>
            </ICMS60>
          </ICMS>
          <PIS>
            <PISNT>
              <CST>06</CST>
            </PISNT>
          </PIS>
          <COFINS>
            <COFINSNT>
              <CST>06</CST>
            </COFINSNT>
          </COFINS>
        </imposto>
      </det>
      <det nItem="5">
        <prod>
          <cProd>47709</cProd>
          <cEAN>7891962054575</cEAN>
          <xProd>Bisc Waffer Bauducco</xProd>
          <NCM>19053200</NCM>
          <CEST>1705800</CEST>
          <CFOP>5405</CFOP>
          <uCom>UN</uCom>
          <qCom>1.0000</qCom>
          <vUnCom>1.4900000000</vUnCom>
          <vProd>1.49</vProd>
          <cEANTrib>7891962054575</cEANTrib>
          <uTrib>UN</uTrib>
          <qTrib>1.0000</qTrib>
          <vUnTrib>1.4900000000</vUnTrib>
          <indTot>1</indTot>
        </prod>
        <imposto>
          <vTotTrib>0.00</vTotTrib>
          <ICMS>
            <ICMS60>
              <orig>0</orig>
              <CST>60</CST>
              <pRedBCEfet>0.00</pRedBCEfet>
              <vBCEfet>1.49</vBCEfet>
              <pICMSEfet>0.00</pICMSEfet>
              <vICMSEfet>0.00</vICMSEfet>
            </ICMS60>
          </ICMS>
          <PIS>
            <PISAliq>
              <CST>01</CST>
              <vBC>1.49</vBC>
              <pPIS>1.65</pPIS>
              <vPIS>0.02</vPIS>
            </PISAliq>
          </PIS>
          <COFINS>
            <COFINSAliq>
              <CST>01</CST>
              <vBC>1.49</vBC>
              <pCOFINS>7.60</pCOFINS>
              <vCOFINS>0.11</vCOFINS>
            </COFINSAliq>
          </COFINS>
        </imposto>
      </det>
      <det nItem="6">
        <prod>
          <cProd>46588</cProd>
          <cEAN>7891962054568</cEAN>
          <xProd>Bisc Waffer Bauducco</xProd>
          <NCM>19053200</NCM>
          <CEST>1705800</CEST>
          <CFOP>5405</CFOP>
          <uCom>UN</uCom>
          <qCom>1.0000</qCom>
          <vUnCom>1.4900000000</vUnCom>
          <vProd>1.49</vProd>
          <cEANTrib>7891962054568</cEANTrib>
          <uTrib>UN</uTrib>
          <qTrib>1.0000</qTrib>
          <vUnTrib>1.4900000000</vUnTrib>
          <indTot>1</indTot>
        </prod>
        <imposto>
          <vTotTrib>0.00</vTotTrib>
          <ICMS>
            <ICMS60>
              <orig>0</orig>
              <CST>60</CST>
              <pRedBCEfet>0.00</pRedBCEfet>
              <vBCEfet>1.49</vBCEfet>
              <pICMSEfet>0.00</pICMSEfet>
              <vICMSEfet>0.00</vICMSEfet>
            </ICMS60>
          </ICMS>
          <PIS>
            <PISAliq>
              <CST>01</CST>
              <vBC>1.49</vBC>
              <pPIS>1.65</pPIS>
              <vPIS>0.02</vPIS>
            </PISAliq>
          </PIS>
          <COFINS>
            <COFINSAliq>
              <CST>01</CST>
              <vBC>1.49</vBC>
              <pCOFINS>7.60</pCOFINS>
              <vCOFINS>0.11</vCOFINS>
            </COFINSAliq>
          </COFINS>
        </imposto>
      </det>
      <det nItem="7">
        <prod>
          <cProd>47709</cProd>
          <cEAN>7891962054575</cEAN>
          <xProd>Bisc Waffer Bauducco</xProd>
          <NCM>19053200</NCM>
          <CEST>1705800</CEST>
          <CFOP>5405</CFOP>
          <uCom>UN</uCom>
          <qCom>1.0000</qCom>
          <vUnCom>1.4900000000</vUnCom>
          <vProd>1.49</vProd>
          <cEANTrib>7891962054575</cEANTrib>
          <uTrib>UN</uTrib>
          <qTrib>1.0000</qTrib>
          <vUnTrib>1.4900000000</vUnTrib>
          <indTot>1</indTot>
        </prod>
        <imposto>
          <vTotTrib>0.00</vTotTrib>
          <ICMS>
            <ICMS60>
              <orig>0</orig>
              <CST>60</CST>
              <pRedBCEfet>0.00</pRedBCEfet>
              <vBCEfet>1.49</vBCEfet>
              <pICMSEfet>0.00</pICMSEfet>
              <vICMSEfet>0.00</vICMSEfet>
            </ICMS60>
          </ICMS>
          <PIS>
            <PISAliq>
              <CST>01</CST>
              <vBC>1.49</vBC>
              <pPIS>1.65</pPIS>
              <vPIS>0.02</vPIS>
            </PISAliq>
          </PIS>
          <COFINS>
            <COFINSAliq>
              <CST>01</CST>
              <vBC>1.49</vBC>
              <pCOFINS>7.60</pCOFINS>
              <vCOFINS>0.11</vCOFINS>
            </COFINSAliq>
          </COFINS>
        </imposto>
      </det>
      <det nItem="8">
        <prod>
          <cProd>6011</cProd>
          <cEAN>7896259415367</cEAN>
          <xProd>Leite Em Po Inst Cam</xProd>
          <NCM>04022110</NCM>
          <CFOP>5405</CFOP>
          <uCom>UN</uCom>
          <qCom>1.0000</qCom>
          <vUnCom>24.1900000000</vUnCom>
          <vProd>24.19</vProd>
          <cEANTrib>7896259415367</cEANTrib>
          <uTrib>UN</uTrib>
          <qTrib>1.0000</qTrib>
          <vUnTrib>24.1900000000</vUnTrib>
          <indTot>1</indTot>
        </prod>
        <imposto>
          <vTotTrib>0.00</vTotTrib>
          <ICMS>
            <ICMS60>
              <orig>1</orig>
              <CST>60</CST>
              <pRedBCEfet>0.00</pRedBCEfet>
              <vBCEfet>24.19</vBCEfet>
              <pICMSEfet>0.00</pICMSEfet>
              <vICMSEfet>0.00</vICMSEfet>
            </ICMS60>
          </ICMS>
          <PIS>
            <PISNT>
              <CST>06</CST>
            </PISNT>
          </PIS>
          <COFINS>
            <COFINSNT>
              <CST>06</CST>
            </COFINSNT>
          </COFINS>
        </imposto>
      </det>
      <det nItem="9">
        <prod>
          <cProd>48607</cProd>
          <cEAN>7896259411628</cEAN>
          <xProd>Cr De Leite Campones</xProd>
          <NCM>04015021</NCM>
          <CEST>1701902</CEST>
          <CFOP>5405</CFOP>
          <uCom>UN</uCom>
          <qCom>1.0000</qCom>
          <vUnCom>2.2900000000</vUnCom>
          <vProd>2.29</vProd>
          <cEANTrib>7896259411628</cEANTrib>
          <uTrib>UN</uTrib>
          <qTrib>1.0000</qTrib>
          <vUnTrib>2.2900000000</vUnTrib>
          <indTot>1</indTot>
        </prod>
        <imposto>
          <vTotTrib>0.00</vTotTrib>
          <ICMS>
            <ICMS60>
              <orig>0</orig>
              <CST>60</CST>
              <pRedBCEfet>0.00</pRedBCEfet>
              <vBCEfet>2.29</vBCEfet>
              <pICMSEfet>0.00</pICMSEfet>
              <vICMSEfet>0.00</vICMSEfet>
            </ICMS60>
          </ICMS>
          <PIS>
            <PISAliq>
              <CST>01</CST>
              <vBC>2.29</vBC>
              <pPIS>1.65</pPIS>
              <vPIS>0.04</vPIS>
            </PISAliq>
          </PIS>
          <COFINS>
            <COFINSAliq>
              <CST>01</CST>
              <vBC>2.29</vBC>
              <pCOFINS>7.60</pCOFINS>
              <vCOFINS>0.17</vCOFINS>
            </COFINSAliq>
          </COFINS>
        </imposto>
      </det>
      <det nItem="10">
        <prod>
          <cProd>64</cProd>
          <cEAN>7898029650022</cEAN>
          <xProd>Goiabada Poly 300g</xProd>
          <NCM>20079990</NCM>
          <CFOP>5405</CFOP>
          <uCom>UN</uCom>
          <qCom>1.0000</qCom>
          <vUnCom>2.3500000000</vUnCom>
          <vProd>2.35</vProd>
          <cEANTrib>7898029650022</cEANTrib>
          <uTrib>UN</uTrib>
          <qTrib>1.0000</qTrib>
          <vUnTrib>2.3500000000</vUnTrib>
          <indTot>1</indTot>
        </prod>
        <imposto>
          <vTotTrib>0.00</vTotTrib>
          <ICMS>
            <ICMS60>
              <orig>0</orig>
              <CST>60</CST>
              <pRedBCEfet>0.00</pRedBCEfet>
              <vBCEfet>2.35</vBCEfet>
              <pICMSEfet>0.00</pICMSEfet>
              <vICMSEfet>0.00</vICMSEfet>
            </ICMS60>
          </ICMS>
          <PIS>
            <PISAliq>
              <CST>01</CST>
              <vBC>2.35</vBC>
              <pPIS>1.65</pPIS>
              <vPIS>0.04</vPIS>
            </PISAliq>
          </PIS>
          <COFINS>
            <COFINSAliq>
              <CST>01</CST>
              <vBC>2.35</vBC>
              <pCOFINS>7.60</pCOFINS>
              <vCOFINS>0.18</vCOFINS>
            </COFINSAliq>
          </COFINS>
        </imposto>
      </det>
      <det nItem="11">
        <prod>
          <cProd>14779</cProd>
          <cEAN>7896016411014</cEAN>
          <xProd>Mac. Espag. Pajucara</xProd>
          <NCM>19021900</NCM>
          <CEST>1704900</CEST>
          <CFOP>5405</CFOP>
          <uCom>UN</uCom>
          <qCom>2.0000</qCom>
          <vUnCom>2.5500000000</vUnCom>
          <vProd>5.10</vProd>
          <cEANTrib>7896016411014</cEANTrib>
          <uTrib>UN</uTrib>
          <qTrib>2.0000</qTrib>
          <vUnTrib>2.5500000000</vUnTrib>
          <indTot>1</indTot>
        </prod>
        <imposto>
          <vTotTrib>0.00</vTotTrib>
          <ICMS>
            <ICMS60>
              <orig>0</orig>
              <CST>60</CST>
              <pRedBCEfet>0.00</pRedBCEfet>
              <vBCEfet>5.10</vBCEfet>
              <pICMSEfet>0.00</pICMSEfet>
              <vICMSEfet>0.00</vICMSEfet>
            </ICMS60>
          </ICMS>
          <PIS>
            <PISNT>
              <CST>06</CST>
            </PISNT>
          </PIS>
          <COFINS>
            <COFINSNT>
              <CST>06</CST>
            </COFINSNT>
          </COFINS>
        </imposto>
      </det>
      <det nItem="12">
        <prod>
          <cProd>47144</cProd>
          <cEAN>7896085391118</cEAN>
          <xProd>Achoc Boa Vida Uht T</xProd>
          <NCM>22029900</NCM>
          <CEST>1711500</CEST>
          <CFOP>5405</CFOP>
          <uCom>UN</uCom>
          <qCom>1.0000</qCom>
          <vUnCom>4.9400000000</vUnCom>
          <vProd>4.94</vProd>
          <cEANTrib>7896085391118</cEANTrib>
          <uTrib>UN</uTrib>
          <qTrib>1.0000</qTrib>
          <vUnTrib>4.9400000000</vUnTrib>
          <indTot>1</indTot>
        </prod>
        <imposto>
          <vTotTrib>0.00</vTotTrib>
          <ICMS>
            <ICMS60>
              <orig>0</orig>
              <CST>60</CST>
              <pRedBCEfet>0.00</pRedBCEfet>
              <vBCEfet>4.94</vBCEfet>
              <pICMSEfet>0.00</pICMSEfet>
              <vICMSEfet>0.00</vICMSEfet>
            </ICMS60>
          </ICMS>
          <PIS>
            <PISOutr>
              <CST>99</CST>
              <vBC>4.94</vBC>
              <pPIS>0</pPIS>
              <vPIS>0</vPIS>
            </PISOutr>
          </PIS>
          <COFINS>
            <COFINSOutr>
              <CST>99</CST>
              <vBC>4.94</vBC>
              <pCOFINS>0</pCOFINS>
              <vCOFINS>0</vCOFINS>
            </COFINSOutr>
          </COFINS>
        </imposto>
      </det>
      <det nItem="13">
        <prod>
          <cProd>48357</cProd>
          <cEAN>7891000073100</cEAN>
          <xProd>Mucilon Arroz E Avei</xProd>
          <NCM>19011030</NCM>
          <CEST>1701500</CEST>
          <CFOP>5405</CFOP>
          <uCom>UN</uCom>
          <qCom>1.0000</qCom>
          <vUnCom>11.2900000000</vUnCom>
          <vProd>11.29</vProd>
          <cEANTrib>7891000073100</cEANTrib>
          <uTrib>UN</uTrib>
          <qTrib>1.0000</qTrib>
          <vUnTrib>11.2900000000</vUnTrib>
          <indTot>1</indTot>
        </prod>
        <imposto>
          <vTotTrib>0.00</vTotTrib>
          <ICMS>
            <ICMS60>
              <orig>0</orig>
              <CST>60</CST>
              <pRedBCEfet>0.00</pRedBCEfet>
              <vBCEfet>11.29</vBCEfet>
              <pICMSEfet>0.00</pICMSEfet>
              <vICMSEfet>0.00</vICMSEfet>
            </ICMS60>
          </ICMS>
          <PIS>
            <PISAliq>
              <CST>01</CST>
              <vBC>11.29</vBC>
              <pPIS>1.65</pPIS>
              <vPIS>0.19</vPIS>
            </PISAliq>
          </PIS>
          <COFINS>
            <COFINSAliq>
              <CST>01</CST>
              <vBC>11.29</vBC>
              <pCOFINS>7.60</pCOFINS>
              <vCOFINS>0.86</vCOFINS>
            </COFINSAliq>
          </COFINS>
        </imposto>
      </det>
      <det nItem="14">
        <prod>
          <cProd>46616</cProd>
          <cEAN>7896009301049</cEAN>
          <xProd>Sard Coqueiro Oleo 1</xProd>
          <NCM>16041310</NCM>
          <CEST>1708100</CEST>
          <CFOP>5405</CFOP>
          <uCom>UN</uCom>
          <qCom>2.0000</qCom>
          <vUnCom>4.4500000000</vUnCom>
          <vProd>8.90</vProd>
          <cEANTrib>7896009301049</cEANTrib>
          <uTrib>UN</uTrib>
          <qTrib>2.0000</qTrib>
          <vUnTrib>4.4500000000</vUnTrib>
          <indTot>1</indTot>
        </prod>
        <imposto>
          <vTotTrib>0.00</vTotTrib>
          <ICMS>
            <ICMS60>
              <orig>0</orig>
              <CST>60</CST>
              <pRedBCEfet>0.00</pRedBCEfet>
              <vBCEfet>8.90</vBCEfet>
              <pICMSEfet>0.00</pICMSEfet>
              <vICMSEfet>0.00</vICMSEfet>
            </ICMS60>
          </ICMS>
          <PIS>
            <PISAliq>
              <CST>01</CST>
              <vBC>8.90</vBC>
              <pPIS>1.65</pPIS>
              <vPIS>0.15</vPIS>
            </PISAliq>
          </PIS>
          <COFINS>
            <COFINSAliq>
              <CST>01</CST>
              <vBC>8.90</vBC>
              <pCOFINS>7.60</pCOFINS>
              <vCOFINS>0.68</vCOFINS>
            </COFINSAliq>
          </COFINS>
        </imposto>
      </det>
      <det nItem="15">
        <prod>
          <cProd>46612</cProd>
          <cEAN>7896102509410</cEAN>
          <xProd>Molho Pr Quero Tradi</xProd>
          <NCM>21032010</NCM>
          <CEST>1704100</CEST>
          <CFOP>5405</CFOP>
          <uCom>UN</uCom>
          <qCom>2.0000</qCom>
          <vUnCom>1.9900000000</vUnCom>
          <vProd>3.98</vProd>
          <cEANTrib>7896102509410</cEANTrib>
          <uTrib>UN</uTrib>
          <qTrib>2.0000</qTrib>
          <vUnTrib>1.9900000000</vUnTrib>
          <indTot>1</indTot>
        </prod>
        <imposto>
          <vTotTrib>0.00</vTotTrib>
          <ICMS>
            <ICMS60>
              <orig>0</orig>
              <CST>60</CST>
              <pRedBCEfet>0.00</pRedBCEfet>
              <vBCEfet>3.98</vBCEfet>
              <pICMSEfet>0.00</pICMSEfet>
              <vICMSEfet>0.00</vICMSEfet>
            </ICMS60>
          </ICMS>
          <PIS>
            <PISAliq>
              <CST>01</CST>
              <vBC>3.98</vBC>
              <pPIS>1.65</pPIS>
              <vPIS>0.07</vPIS>
            </PISAliq>
          </PIS>
          <COFINS>
            <COFINSAliq>
              <CST>01</CST>
              <vBC>3.98</vBC>
              <pCOFINS>7.60</pCOFINS>
              <vCOFINS>0.30</vCOFINS>
            </COFINSAliq>
          </COFINS>
        </imposto>
      </det>
      <det nItem="16">
        <prod>
          <cProd>58085</cProd>
          <cEAN>7896490288898</cEAN>
          <xProd>Colorifico Dona Clar</xProd>
          <NCM>21039021</NCM>
          <CEST>1703500</CEST>
          <CFOP>5405</CFOP>
          <uCom>UN</uCom>
          <qCom>1.0000</qCom>
          <vUnCom>0.8900000000</vUnCom>
          <vProd>0.89</vProd>
          <cEANTrib>7896490288898</cEANTrib>
          <uTrib>UN</uTrib>
          <qTrib>1.0000</qTrib>
          <vUnTrib>0.8900000000</vUnTrib>
          <indTot>1</indTot>
        </prod>
        <imposto>
          <vTotTrib>0.00</vTotTrib>
          <ICMS>
            <ICMS60>
              <orig>0</orig>
              <CST>60</CST>
              <pRedBCEfet>0.00</pRedBCEfet>
              <vBCEfet>0.89</vBCEfet>
              <pICMSEfet>0.00</pICMSEfet>
              <vICMSEfet>0.00</vICMSEfet>
            </ICMS60>
          </ICMS>
          <PIS>
            <PISAliq>
              <CST>01</CST>
              <vBC>0.89</vBC>
              <pPIS>1.65</pPIS>
              <vPIS>0.01</vPIS>
            </PISAliq>
          </PIS>
          <COFINS>
            <COFINSAliq>
              <CST>01</CST>
              <vBC>0.89</vBC>
              <pCOFINS>7.60</pCOFINS>
              <vCOFINS>0.07</vCOFINS>
            </COFINSAliq>
          </COFINS>
        </imposto>
      </det>
      <det nItem="17">
        <prod>
          <cProd>14432</cProd>
          <cEAN>7896013104919</cEAN>
          <xProd>Vinagre Minhoto Alco</xProd>
          <NCM>22090000</NCM>
          <CFOP>5102</CFOP>
          <uCom>UN</uCom>
          <qCom>1.0000</qCom>
          <vUnCom>3.8100000000</vUnCom>
          <vProd>3.81</vProd>
          <cEANTrib>7896013104919</cEANTrib>
          <uTrib>UN</uTrib>
          <qTrib>1.0000</qTrib>
          <vUnTrib>3.8100000000</vUnTrib>
          <indTot>1</indTot>
        </prod>
        <imposto>
          <vTotTrib>0.00</vTotTrib>
          <ICMS>
            <ICMS20>
              <orig>0</orig>
              <CST>20</CST>
              <modBC>3</modBC>
              <pRedBC>58.82</pRedBC>
              <vBC>1.57</vBC>
              <pICMS>17.00</pICMS>
              <vICMS>0.27</vICMS>
              <vICMSDeson>0.38</vICMSDeson>
              <motDesICMS>9</motDesICMS>
            </ICMS20>
          </ICMS>
          <PIS>
            <PISAliq>
              <CST>01</CST>
              <vBC>3.81</vBC>
              <pPIS>1.65</pPIS>
              <vPIS>0.06</vPIS>
            </PISAliq>
          </PIS>
          <COFINS>
            <COFINSAliq>
              <CST>01</CST>
              <vBC>3.81</vBC>
              <pCOFINS>7.60</pCOFINS>
              <vCOFINS>0.29</vCOFINS>
            </COFINSAliq>
          </COFINS>
        </imposto>
      </det>
      <det nItem="18">
        <prod>
          <cProd>46590</cProd>
          <cEAN>7896481130137</cEAN>
          <xProd>Flocao De Milho Cori</xProd>
          <NCM>11041900</NCM>
          <CFOP>5102</CFOP>
          <uCom>UN</uCom>
          <qCom>10.0000</qCom>
          <vUnCom>1.9900000000</vUnCom>
          <vProd>19.90</vProd>
          <cEANTrib>7896481130137</cEANTrib>
          <uTrib>UN</uTrib>
          <qTrib>10.0000</qTrib>
          <vUnTrib>1.9900000000</vUnTrib>
          <indTot>1</indTot>
        </prod>
        <imposto>
          <vTotTrib>0.00</vTotTrib>
          <ICMS>
            <ICMS20>
              <orig>0</orig>
              <CST>20</CST>
              <modBC>3</modBC>
              <pRedBC>58.82</pRedBC>
              <vBC>8.19</vBC>
              <pICMS>17.00</pICMS>
              <vICMS>1.39</vICMS>
              <vICMSDeson>1.99</vICMSDeson>
              <motDesICMS>9</motDesICMS>
            </ICMS20>
          </ICMS>
          <PIS>
            <PISOutr>
              <CST>49</CST>
              <vBC>19.90</vBC>
              <pPIS>0</pPIS>
              <vPIS>0</vPIS>
            </PISOutr>
          </PIS>
          <COFINS>
            <COFINSOutr>
              <CST>49</CST>
              <vBC>19.90</vBC>
              <pCOFINS>0</pCOFINS>
              <vCOFINS>0</vCOFINS>
            </COFINSOutr>
          </COFINS>
        </imposto>
      </det>
      <det nItem="19">
        <prod>
          <cProd>46597</cProd>
          <cEAN>7896084700027</cEAN>
          <xProd>Arroz Kiarroz Parb T</xProd>
          <NCM>10063011</NCM>
          <CFOP>5102</CFOP>
          <uCom>UN</uCom>
          <qCom>6.0000</qCom>
          <vUnCom>3.1900000000</vUnCom>
          <vProd>19.14</vProd>
          <cEANTrib>7896084700027</cEANTrib>
          <uTrib>UN</uTrib>
          <qTrib>6.0000</qTrib>
          <vUnTrib>3.1900000000</vUnTrib>
          <indTot>1</indTot>
        </prod>
        <imposto>
          <vTotTrib>0.00</vTotTrib>
          <ICMS>
            <ICMS20>
              <orig>0</orig>
              <CST>20</CST>
              <modBC>3</modBC>
              <pRedBC>58.82</pRedBC>
              <vBC>7.88</vBC>
              <pICMS>17.00</pICMS>
              <vICMS>1.34</vICMS>
              <vICMSDeson>1.91</vICMSDeson>
              <motDesICMS>9</motDesICMS>
            </ICMS20>
          </ICMS>
          <PIS>
            <PISNT>
              <CST>06</CST>
            </PISNT>
          </PIS>
          <COFINS>
            <COFINSNT>
              <CST>06</CST>
            </COFINSNT>
          </COFINS>
        </imposto>
      </det>
      <det nItem="20">
        <prod>
          <cProd>46765</cProd>
          <cEAN>7896481130069</cEAN>
          <xProd>Milho De Pipoca Cori</xProd>
          <NCM>11042300</NCM>
          <CFOP>5102</CFOP>
          <uCom>UN</uCom>
          <qCom>1.0000</qCom>
          <vUnCom>3.9900000000</vUnCom>
          <vProd>3.99</vProd>
          <cEANTrib>7896481130069</cEANTrib>
          <uTrib>UN</uTrib>
          <qTrib>1.0000</qTrib>
          <vUnTrib>3.9900000000</vUnTrib>
          <indTot>1</indTot>
        </prod>
        <imposto>
          <vTotTrib>0.00</vTotTrib>
          <ICMS>
            <ICMS00>
              <orig>0</orig>
              <CST>00</CST>
              <modBC>3</modBC>
              <vBC>3.99</vBC>
              <pICMS>18.00</pICMS>
              <vICMS>0.72</vICMS>
            </ICMS00>
          </ICMS>
          <PIS>
            <PISAliq>
              <CST>01</CST>
              <vBC>3.99</vBC>
              <pPIS>1.65</pPIS>
              <vPIS>0.07</vPIS>
            </PISAliq>
          </PIS>
          <COFINS>
            <COFINSAliq>
              <CST>01</CST>
              <vBC>3.99</vBC>
              <pCOFINS>7.60</pCOFINS>
              <vCOFINS>0.30</vCOFINS>
            </COFINSAliq>
          </COFINS>
        </imposto>
      </det>
      <det nItem="21">
        <prod>
          <cProd>47046</cProd>
          <cEAN>7897261800011</cEAN>
          <xProd>Acucar Caete Branco</xProd>
          <NCM>17019900</NCM>
          <CEST>1709900</CEST>
          <CFOP>5405</CFOP>
          <uCom>UN</uCom>
          <qCom>6.0000</qCom>
          <vUnCom>3.4900000000</vUnCom>
          <vProd>20.94</vProd>
          <cEANTrib>7897261800011</cEANTrib>
          <uTrib>UN</uTrib>
          <qTrib>6.0000</qTrib>
          <vUnTrib>3.4900000000</vUnTrib>
          <indTot>1</indTot>
        </prod>
        <imposto>
          <vTotTrib>0.00</vTotTrib>
          <ICMS>
            <ICMS60>
              <orig>0</orig>
              <CST>60</CST>
              <pRedBCEfet>0.00</pRedBCEfet>
              <vBCEfet>20.94</vBCEfet>
              <pICMSEfet>0.00</pICMSEfet>
              <vICMSEfet>0.00</vICMSEfet>
            </ICMS60>
          </ICMS>
          <PIS>
            <PISNT>
              <CST>06</CST>
            </PISNT>
          </PIS>
          <COFINS>
            <COFINSNT>
              <CST>06</CST>
            </COFINSNT>
          </COFINS>
        </imposto>
      </det>
      <det nItem="22">
        <prod>
          <cProd>12631</cProd>
          <cEAN>7891079011812</cEAN>
          <xProd>Mac Inst N. Sabor Ca</xProd>
          <NCM>19023000</NCM>
          <CEST>1704701</CEST>
          <CFOP>5405</CFOP>
          <uCom>UN</uCom>
          <qCom>3.0000</qCom>
          <vUnCom>0.8900000000</vUnCom>
          <vProd>2.67</vProd>
          <cEANTrib>7891079011812</cEANTrib>
          <uTrib>UN</uTrib>
          <qTrib>3.0000</qTrib>
          <vUnTrib>0.8900000000</vUnTrib>
          <indTot>1</indTot>
        </prod>
        <imposto>
          <vTotTrib>0.00</vTotTrib>
          <ICMS>
            <ICMS60>
              <orig>0</orig>
              <CST>60</CST>
              <pRedBCEfet>0.00</pRedBCEfet>
              <vBCEfet>2.67</vBCEfet>
              <pICMSEfet>0.00</pICMSEfet>
              <vICMSEfet>0.00</vICMSEfet>
            </ICMS60>
          </ICMS>
          <PIS>
            <PISNT>
              <CST>06</CST>
            </PISNT>
          </PIS>
          <COFINS>
            <COFINSNT>
              <CST>06</CST>
            </COFINSNT>
          </COFINS>
        </imposto>
      </det>
      <det nItem="23">
        <prod>
          <cProd>46591</cProd>
          <cEAN>7896102500899</cEAN>
          <xProd>Duet Quero Milho Erv</xProd>
          <NCM>20059900</NCM>
          <CEST>1709200</CEST>
          <CFOP>5405</CFOP>
          <uCom>UN</uCom>
          <qCom>2.0000</qCom>
          <vUnCom>3.3100000000</vUnCom>
          <vProd>6.62</vProd>
          <cEANTrib>7896102500899</cEANTrib>
          <uTrib>UN</uTrib>
          <qTrib>2.0000</qTrib>
          <vUnTrib>3.3100000000</vUnTrib>
          <indTot>1</indTot>
        </prod>
        <imposto>
          <vTotTrib>0.00</vTotTrib>
          <ICMS>
            <ICMS60>
              <orig>0</orig>
              <CST>60</CST>
              <pRedBCEfet>0.00</pRedBCEfet>
              <vBCEfet>6.62</vBCEfet>
              <pICMSEfet>0.00</pICMSEfet>
              <vICMSEfet>0.00</vICMSEfet>
            </ICMS60>
          </ICMS>
          <PIS>
            <PISAliq>
              <CST>01</CST>
              <vBC>6.62</vBC>
              <pPIS>1.65</pPIS>
              <vPIS>0.11</vPIS>
            </PISAliq>
          </PIS>
          <COFINS>
            <COFINSAliq>
              <CST>01</CST>
              <vBC>6.62</vBC>
              <pCOFINS>7.60</pCOFINS>
              <vCOFINS>0.50</vCOFINS>
            </COFINSAliq>
          </COFINS>
        </imposto>
      </det>
      <det nItem="24">
        <prod>
          <cProd>46440</cProd>
          <cEAN>7891150068285</cEAN>
          <xProd>Amido Milho Arrozina</xProd>
          <NCM>19011030</NCM>
          <CEST>1701500</CEST>
          <CFOP>5405</CFOP>
          <uCom>UN</uCom>
          <qCom>1.0000</qCom>
          <vUnCom>3.7900000000</vUnCom>
          <vProd>3.79</vProd>
          <cEANTrib>7891150068285</cEANTrib>
          <uTrib>UN</uTrib>
          <qTrib>1.0000</qTrib>
          <vUnTrib>3.7900000000</vUnTrib>
          <indTot>1</indTot>
        </prod>
        <imposto>
          <vTotTrib>0.00</vTotTrib>
          <ICMS>
            <ICMS60>
              <orig>0</orig>
              <CST>60</CST>
              <pRedBCEfet>0.00</pRedBCEfet>
              <vBCEfet>3.79</vBCEfet>
              <pICMSEfet>0.00</pICMSEfet>
              <vICMSEfet>0.00</vICMSEfet>
            </ICMS60>
          </ICMS>
          <PIS>
            <PISAliq>
              <CST>01</CST>
              <vBC>3.79</vBC>
              <pPIS>1.65</pPIS>
              <vPIS>0.06</vPIS>
            </PISAliq>
          </PIS>
          <COFINS>
            <COFINSAliq>
              <CST>01</CST>
              <vBC>3.79</vBC>
              <pCOFINS>7.60</pCOFINS>
              <vCOFINS>0.29</vCOFINS>
            </COFINSAliq>
          </COFINS>
        </imposto>
      </det>
      <det nItem="25">
        <prod>
          <cProd>40742</cProd>
          <cEAN>7891079011805</cEAN>
          <xProd>Mac Inst N. Sabor Ga</xProd>
          <NCM>19023000</NCM>
          <CEST>1704701</CEST>
          <CFOP>5405</CFOP>
          <uCom>UN</uCom>
          <qCom>3.0000</qCom>
          <vUnCom>0.8900000000</vUnCom>
          <vProd>2.67</vProd>
          <cEANTrib>7891079011805</cEANTrib>
          <uTrib>UN</uTrib>
          <qTrib>3.0000</qTrib>
          <vUnTrib>0.8900000000</vUnTrib>
          <indTot>1</indTot>
        </prod>
        <imposto>
          <vTotTrib>0.00</vTotTrib>
          <ICMS>
            <ICMS60>
              <orig>0</orig>
              <CST>60</CST>
              <pRedBCEfet>0.00</pRedBCEfet>
              <vBCEfet>2.67</vBCEfet>
              <pICMSEfet>0.00</pICMSEfet>
              <vICMSEfet>0.00</vICMSEfet>
            </ICMS60>
          </ICMS>
          <PIS>
            <PISNT>
              <CST>06</CST>
            </PISNT>
          </PIS>
          <COFINS>
            <COFINSNT>
              <CST>06</CST>
            </COFINSNT>
          </COFINS>
        </imposto>
      </det>
      <det nItem="26">
        <prod>
          <cProd>57069</cProd>
          <cEAN>7891079011829</cEAN>
          <xProd>Mac Inst Nosso Sabor</xProd>
          <NCM>19023000</NCM>
          <CEST>1704701</CEST>
          <CFOP>5405</CFOP>
          <uCom>UN</uCom>
          <qCom>3.0000</qCom>
          <vUnCom>0.8900000000</vUnCom>
          <vProd>2.67</vProd>
          <cEANTrib>7891079011829</cEANTrib>
          <uTrib>UN</uTrib>
          <qTrib>3.0000</qTrib>
          <vUnTrib>0.8900000000</vUnTrib>
          <indTot>1</indTot>
        </prod>
        <imposto>
          <vTotTrib>0.00</vTotTrib>
          <ICMS>
            <ICMS60>
              <orig>0</orig>
              <CST>60</CST>
              <pRedBCEfet>0.00</pRedBCEfet>
              <vBCEfet>2.67</vBCEfet>
              <pICMSEfet>0.00</pICMSEfet>
              <vICMSEfet>0.00</vICMSEfet>
            </ICMS60>
          </ICMS>
          <PIS>
            <PISNT>
              <CST>06</CST>
            </PISNT>
          </PIS>
          <COFINS>
            <COFINSNT>
              <CST>06</CST>
            </COFINSNT>
          </COFINS>
        </imposto>
      </det>
      <det nItem="27">
        <prod>
          <cProd>46839</cProd>
          <cEAN>78940734</cEAN>
          <xProd>Choc Kinder Joy Meni</xProd>
          <NCM>18069000</NCM>
          <CFOP>5405</CFOP>
          <uCom>UN</uCom>
          <qCom>1.0000</qCom>
          <vUnCom>8.1500000000</vUnCom>
          <vProd>8.15</vProd>
          <cEANTrib>78940734</cEANTrib>
          <uTrib>UN</uTrib>
          <qTrib>1.0000</qTrib>
          <vUnTrib>8.1500000000</vUnTrib>
          <indTot>1</indTot>
        </prod>
        <imposto>
          <vTotTrib>0.00</vTotTrib>
          <ICMS>
            <ICMS60>
              <orig>0</orig>
              <CST>60</CST>
              <pRedBCEfet>0.00</pRedBCEfet>
              <vBCEfet>8.15</vBCEfet>
              <pICMSEfet>0.00</pICMSEfet>
              <vICMSEfet>0.00</vICMSEfet>
            </ICMS60>
          </ICMS>
          <PIS>
            <PISAliq>
              <CST>01</CST>
              <vBC>8.15</vBC>
              <pPIS>1.65</pPIS>
              <vPIS>0.13</vPIS>
            </PISAliq>
          </PIS>
          <COFINS>
            <COFINSAliq>
              <CST>01</CST>
              <vBC>8.15</vBC>
              <pCOFINS>7.60</pCOFINS>
              <vCOFINS>0.62</vCOFINS>
            </COFINSAliq>
          </COFINS>
        </imposto>
      </det>
      <det nItem="28">
        <prod>
          <cProd>1961</cProd>
          <cEAN>7891000379103</cEAN>
          <xProd>Achoc. Liq Nescau 20</xProd>
          <NCM>22029900</NCM>
          <CEST>1711500</CEST>
          <CFOP>5405</CFOP>
          <uCom>UN</uCom>
          <qCom>5.0000</qCom>
          <vUnCom>1.7900000000</vUnCom>
          <vProd>8.95</vProd>
          <cEANTrib>7891000379103</cEANTrib>
          <uTrib>UN</uTrib>
          <qTrib>5.0000</qTrib>
          <vUnTrib>1.7900000000</vUnTrib>
          <indTot>1</indTot>
        </prod>
        <imposto>
          <vTotTrib>0.00</vTotTrib>
          <ICMS>
            <ICMS60>
              <orig>0</orig>
              <CST>60</CST>
              <pRedBCEfet>0.00</pRedBCEfet>
              <vBCEfet>8.95</vBCEfet>
              <pICMSEfet>0.00</pICMSEfet>
              <vICMSEfet>0.00</vICMSEfet>
            </ICMS60>
          </ICMS>
          <PIS>
            <PISOutr>
              <CST>99</CST>
              <vBC>8.95</vBC>
              <pPIS>0</pPIS>
              <vPIS>0</vPIS>
            </PISOutr>
          </PIS>
          <COFINS>
            <COFINSOutr>
              <CST>99</CST>
              <vBC>8.95</vBC>
              <pCOFINS>0</pCOFINS>
              <vCOFINS>0</vCOFINS>
            </COFINSOutr>
          </COFINS>
        </imposto>
      </det>
      <det nItem="29">
        <prod>
          <cProd>42706</cProd>
          <cEAN>7896013107934</cEAN>
          <xProd>Sabonete Even Flor P</xProd>
          <NCM>34011190</NCM>
          <CEST>2003400</CEST>
          <CFOP>5405</CFOP>
          <uCom>UN</uCom>
          <qCom>1.0000</qCom>
          <vUnCom>1.6000000000</vUnCom>
          <vProd>1.60</vProd>
          <cEANTrib>7896013107934</cEANTrib>
          <uTrib>UN</uTrib>
          <qTrib>1.0000</qTrib>
          <vUnTrib>1.6000000000</vUnTrib>
          <indTot>1</indTot>
        </prod>
        <imposto>
          <vTotTrib>0.00</vTotTrib>
          <ICMS>
            <ICMS60>
              <orig>0</orig>
              <CST>60</CST>
              <pRedBCEfet>0.00</pRedBCEfet>
              <vBCEfet>1.60</vBCEfet>
              <pICMSEfet>0.00</pICMSEfet>
              <vICMSEfet>0.00</vICMSEfet>
            </ICMS60>
          </ICMS>
          <PIS>
            <PISNT>
              <CST>06</CST>
            </PISNT>
          </PIS>
          <COFINS>
            <COFINSNT>
              <CST>06</CST>
            </COFINSNT>
          </COFINS>
        </imposto>
      </det>
      <det nItem="30">
        <prod>
          <cProd>42699</cProd>
          <cEAN>7896013107842</cEAN>
          <xProd>Sabonete Even Mant.s</xProd>
          <NCM>34011190</NCM>
          <CEST>2003400</CEST>
          <CFOP>5405</CFOP>
          <uCom>UN</uCom>
          <qCom>1.0000</qCom>
          <vUnCom>1.6500000000</vUnCom>
          <vProd>1.65</vProd>
          <cEANTrib>7896013107842</cEANTrib>
          <uTrib>UN</uTrib>
          <qTrib>1.0000</qTrib>
          <vUnTrib>1.6500000000</vUnTrib>
          <indTot>1</indTot>
        </prod>
        <imposto>
          <vTotTrib>0.00</vTotTrib>
          <ICMS>
            <ICMS60>
              <orig>0</orig>
              <CST>60</CST>
              <pRedBCEfet>0.00</pRedBCEfet>
              <vBCEfet>1.65</vBCEfet>
              <pICMSEfet>0.00</pICMSEfet>
              <vICMSEfet>0.00</vICMSEfet>
            </ICMS60>
          </ICMS>
          <PIS>
            <PISNT>
              <CST>06</CST>
            </PISNT>
          </PIS>
          <COFINS>
            <COFINSNT>
              <CST>06</CST>
            </COFINSNT>
          </COFINS>
        </imposto>
      </det>
      <det nItem="31">
        <prod>
          <cProd>42707</cProd>
          <cEAN>7896013107941</cEAN>
          <xProd>Sabonete Even Morang</xProd>
          <NCM>34011190</NCM>
          <CEST>2003400</CEST>
          <CFOP>5405</CFOP>
          <uCom>UN</uCom>
          <qCom>1.0000</qCom>
          <vUnCom>1.5000000000</vUnCom>
          <vProd>1.50</vProd>
          <cEANTrib>7896013107941</cEANTrib>
          <uTrib>UN</uTrib>
          <qTrib>1.0000</qTrib>
          <vUnTrib>1.5000000000</vUnTrib>
          <indTot>1</indTot>
        </prod>
        <imposto>
          <vTotTrib>0.00</vTotTrib>
          <ICMS>
            <ICMS60>
              <orig>0</orig>
              <CST>60</CST>
              <pRedBCEfet>0.00</pRedBCEfet>
              <vBCEfet>1.50</vBCEfet>
              <pICMSEfet>0.00</pICMSEfet>
              <vICMSEfet>0.00</vICMSEfet>
            </ICMS60>
          </ICMS>
          <PIS>
            <PISNT>
              <CST>06</CST>
            </PISNT>
          </PIS>
          <COFINS>
            <COFINSNT>
              <CST>06</CST>
            </COFINSNT>
          </COFINS>
        </imposto>
      </det>
      <det nItem="32">
        <prod>
          <cProd>17436</cProd>
          <cEAN>7891107101621</cEAN>
          <xProd>Oleo De Soja Soya 90</xProd>
          <NCM>15079011</NCM>
          <CEST>1706500</CEST>
          <CFOP>5405</CFOP>
          <uCom>UN</uCom>
          <qCom>2.0000</qCom>
          <vUnCom>8.4900000000</vUnCom>
          <vProd>16.98</vProd>
          <cEANTrib>7891107101621</cEANTrib>
          <uTrib>UN</uTrib>
          <qTrib>2.0000</qTrib>
          <vUnTrib>8.4900000000</vUnTrib>
          <indTot>1</indTot>
        </prod>
        <imposto>
          <vTotTrib>0.00</vTotTrib>
          <ICMS>
            <ICMS60>
              <orig>0</orig>
              <CST>60</CST>
              <pRedBCEfet>0.00</pRedBCEfet>
              <vBCEfet>16.98</vBCEfet>
              <pICMSEfet>0.00</pICMSEfet>
              <vICMSEfet>0.00</vICMSEfet>
            </ICMS60>
          </ICMS>
          <PIS>
            <PISNT>
              <CST>06</CST>
            </PISNT>
          </PIS>
          <COFINS>
            <COFINSNT>
              <CST>06</CST>
            </COFINSNT>
          </COFINS>
        </imposto>
      </det>
      <det nItem="33">
        <prod>
          <cProd>45817</cProd>
          <cEAN>7891528038810</cEAN>
          <xProd>Cr Dent Inf Tandy Mo</xProd>
          <NCM>33061000</NCM>
          <CFOP>5405</CFOP>
          <uCom>UN</uCom>
          <qCom>1.0000</qCom>
          <vUnCom>5.7900000000</vUnCom>
          <vProd>5.79</vProd>
          <cEANTrib>7891528038810</cEANTrib>
          <uTrib>UN</uTrib>
          <qTrib>1.0000</qTrib>
          <vUnTrib>5.7900000000</vUnTrib>
          <indTot>1</indTot>
        </prod>
        <imposto>
          <vTotTrib>0.00</vTotTrib>
          <ICMS>
            <ICMS60>
              <orig>0</orig>
              <CST>60</CST>
              <pRedBCEfet>0.00</pRedBCEfet>
              <vBCEfet>5.79</vBCEfet>
              <pICMSEfet>0.00</pICMSEfet>
              <vICMSEfet>0.00</vICMSEfet>
            </ICMS60>
          </ICMS>
          <PIS>
            <PISNT>
              <CST>06</CST>
            </PISNT>
          </PIS>
          <COFINS>
            <COFINSNT>
              <CST>06</CST>
            </COFINSNT>
          </COFINS>
        </imposto>
      </det>
      <det nItem="34">
        <prod>
          <cProd>85761</cProd>
          <cEAN>7509546665306</cEAN>
          <xProd>Cr Dental Colgate l</xProd>
          <NCM>33061000</NCM>
          <CFOP>5405</CFOP>
          <uCom>UN</uCom>
          <qCom>1.0000</qCom>
          <vUnCom>11.2900000000</vUnCom>
          <vProd>11.29</vProd>
          <cEANTrib>7509546665306</cEANTrib>
          <uTrib>UN</uTrib>
          <qTrib>1.0000</qTrib>
          <vUnTrib>11.2900000000</vUnTrib>
          <indTot>1</indTot>
        </prod>
        <imposto>
          <vTotTrib>0.00</vTotTrib>
          <ICMS>
            <ICMS60>
              <orig>0</orig>
              <CST>60</CST>
              <pRedBCEfet>0.00</pRedBCEfet>
              <vBCEfet>11.29</vBCEfet>
              <pICMSEfet>0.00</pICMSEfet>
              <vICMSEfet>0.00</vICMSEfet>
            </ICMS60>
          </ICMS>
          <PIS>
            <PISNT>
              <CST>06</CST>
            </PISNT>
          </PIS>
          <COFINS>
            <COFINSNT>
              <CST>06</CST>
            </COFINSNT>
          </COFINS>
        </imposto>
      </det>
      <det nItem="35">
        <prod>
          <cProd>49174</cProd>
          <cEAN>78923454</cEAN>
          <xProd>Des Roll On Rexona M</xProd>
          <NCM>33072010</NCM>
          <CEST>2002700</CEST>
          <CFOP>5405</CFOP>
          <uCom>UN</uCom>
          <qCom>1.0000</qCom>
          <vUnCom>6.9900000000</vUnCom>
          <vProd>6.99</vProd>
          <cEANTrib>78923454</cEANTrib>
          <uTrib>UN</uTrib>
          <qTrib>1.0000</qTrib>
          <vUnTrib>6.9900000000</vUnTrib>
          <indTot>1</indTot>
        </prod>
        <imposto>
          <vTotTrib>0.00</vTotTrib>
          <ICMS>
            <ICMS60>
              <orig>0</orig>
              <CST>60</CST>
              <pRedBCEfet>0.00</pRedBCEfet>
              <vBCEfet>6.99</vBCEfet>
              <pICMSEfet>0.00</pICMSEfet>
              <vICMSEfet>0.00</vICMSEfet>
            </ICMS60>
          </ICMS>
          <PIS>
            <PISNT>
              <CST>04</CST>
            </PISNT>
          </PIS>
          <COFINS>
            <COFINSNT>
              <CST>04</CST>
            </COFINSNT>
          </COFINS>
        </imposto>
      </det>
      <det nItem="36">
        <prod>
          <cProd>46695</cProd>
          <cEAN>78924352</cEAN>
          <xProd>Des Roll On Rexona F</xProd>
          <NCM>33072010</NCM>
          <CEST>2002700</CEST>
          <CFOP>5405</CFOP>
          <uCom>UN</uCom>
          <qCom>1.0000</qCom>
          <vUnCom>6.9900000000</vUnCom>
          <vProd>6.99</vProd>
          <cEANTrib>78924352</cEANTrib>
          <uTrib>UN</uTrib>
          <qTrib>1.0000</qTrib>
          <vUnTrib>6.9900000000</vUnTrib>
          <indTot>1</indTot>
        </prod>
        <imposto>
          <vTotTrib>0.00</vTotTrib>
          <ICMS>
            <ICMS60>
              <orig>0</orig>
              <CST>60</CST>
              <pRedBCEfet>0.00</pRedBCEfet>
              <vBCEfet>6.99</vBCEfet>
              <pICMSEfet>0.00</pICMSEfet>
              <vICMSEfet>0.00</vICMSEfet>
            </ICMS60>
          </ICMS>
          <PIS>
            <PISNT>
              <CST>04</CST>
            </PISNT>
          </PIS>
          <COFINS>
            <COFINSNT>
              <CST>04</CST>
            </COFINSNT>
          </COFINS>
        </imposto>
      </det>
      <det nItem="37">
        <prod>
          <cProd>66549</cProd>
          <cEAN>7891150061477</cEAN>
          <xProd>Sabao Em Po Ala Coco</xProd>
          <NCM>34022000</NCM>
          <CEST>1100400</CEST>
          <CFOP>5405</CFOP>
          <uCom>UN</uCom>
          <qCom>1.0000</qCom>
          <vUnCom>6.5900000000</vUnCom>
          <vProd>6.59</vProd>
          <cEANTrib>7891150061477</cEANTrib>
          <uTrib>UN</uTrib>
          <qTrib>1.0000</qTrib>
          <vUnTrib>6.5900000000</vUnTrib>
          <indTot>1</indTot>
        </prod>
        <imposto>
          <vTotTrib>0.00</vTotTrib>
          <ICMS>
            <ICMS60>
              <orig>0</orig>
              <CST>60</CST>
              <pRedBCEfet>0.00</pRedBCEfet>
              <vBCEfet>6.59</vBCEfet>
              <pICMSEfet>0.00</pICMSEfet>
              <vICMSEfet>0.00</vICMSEfet>
            </ICMS60>
          </ICMS>
          <PIS>
            <PISAliq>
              <CST>01</CST>
              <vBC>6.59</vBC>
              <pPIS>1.65</pPIS>
              <vPIS>0.11</vPIS>
            </PISAliq>
          </PIS>
          <COFINS>
            <COFINSAliq>
              <CST>01</CST>
              <vBC>6.59</vBC>
              <pCOFINS>7.60</pCOFINS>
              <vCOFINS>0.50</vCOFINS>
            </COFINSAliq>
          </COFINS>
        </imposto>
      </det>
      <det nItem="38">
        <prod>
          <cProd>43064</cProd>
          <cEAN>7896013107880</cEAN>
          <xProd>Sabon Even Aloe Vera</xProd>
          <NCM>34011190</NCM>
          <CEST>2003400</CEST>
          <CFOP>5405</CFOP>
          <uCom>UN</uCom>
          <qCom>1.0000</qCom>
          <vUnCom>1.6000000000</vUnCom>
          <vProd>1.60</vProd>
          <cEANTrib>7896013107880</cEANTrib>
          <uTrib>UN</uTrib>
          <qTrib>1.0000</qTrib>
          <vUnTrib>1.6000000000</vUnTrib>
          <indTot>1</indTot>
        </prod>
        <imposto>
          <vTotTrib>0.00</vTotTrib>
          <ICMS>
            <ICMS60>
              <orig>0</orig>
              <CST>60</CST>
              <pRedBCEfet>0.00</pRedBCEfet>
              <vBCEfet>1.60</vBCEfet>
              <pICMSEfet>0.00</pICMSEfet>
              <vICMSEfet>0.00</vICMSEfet>
            </ICMS60>
          </ICMS>
          <PIS>
            <PISNT>
              <CST>06</CST>
            </PISNT>
          </PIS>
          <COFINS>
            <COFINSNT>
              <CST>06</CST>
            </COFINSNT>
          </COFINS>
        </imposto>
      </det>
      <det nItem="39">
        <prod>
          <cProd>4570</cProd>
          <cEAN>7896098900130</cEAN>
          <xProd>Sabao Barra Ype Flor</xProd>
          <NCM>34011900</NCM>
          <CEST>2003500</CEST>
          <CFOP>5102</CFOP>
          <uCom>UN</uCom>
          <qCom>1.0000</qCom>
          <vUnCom>8.9900000000</vUnCom>
          <vProd>8.99</vProd>
          <cEANTrib>7896098900130</cEANTrib>
          <uTrib>UN</uTrib>
          <qTrib>1.0000</qTrib>
          <vUnTrib>8.9900000000</vUnTrib>
          <indTot>1</indTot>
        </prod>
        <imposto>
          <vTotTrib>0.00</vTotTrib>
          <ICMS>
            <ICMS00>
              <orig>0</orig>
              <CST>00</CST>
              <modBC>3</modBC>
              <vBC>8.99</vBC>
              <pICMS>18.00</pICMS>
              <vICMS>1.62</vICMS>
            </ICMS00>
          </ICMS>
          <PIS>
            <PISAliq>
              <CST>01</CST>
              <vBC>8.99</vBC>
              <pPIS>1.65</pPIS>
              <vPIS>0.15</vPIS>
            </PISAliq>
          </PIS>
          <COFINS>
            <COFINSAliq>
              <CST>01</CST>
              <vBC>8.99</vBC>
              <pCOFINS>7.60</pCOFINS>
              <vCOFINS>0.68</vCOFINS>
            </COFINSAliq>
          </COFINS>
        </imposto>
      </det>
      <det nItem="40">
        <prod>
          <cProd>50332</cProd>
          <cEAN>7896013511656</cEAN>
          <xProd>Cr Trat Novex Oleo D</xProd>
          <NCM>33059000</NCM>
          <CEST>2002000</CEST>
          <CFOP>5405</CFOP>
          <uCom>UN</uCom>
          <qCom>1.0000</qCom>
          <vUnCom>19.3100000000</vUnCom>
          <vProd>19.31</vProd>
          <cEANTrib>7896013511656</cEANTrib>
          <uTrib>UN</uTrib>
          <qTrib>1.0000</qTrib>
          <vUnTrib>19.3100000000</vUnTrib>
          <indTot>1</indTot>
        </prod>
        <imposto>
          <vTotTrib>0.00</vTotTrib>
          <ICMS>
            <ICMS60>
              <orig>0</orig>
              <CST>60</CST>
              <pRedBCEfet>0.00</pRedBCEfet>
              <vBCEfet>19.31</vBCEfet>
              <pICMSEfet>0.00</pICMSEfet>
              <vICMSEfet>0.00</vICMSEfet>
            </ICMS60>
          </ICMS>
          <PIS>
            <PISNT>
              <CST>04</CST>
            </PISNT>
          </PIS>
          <COFINS>
            <COFINSNT>
              <CST>04</CST>
            </COFINSNT>
          </COFINS>
        </imposto>
      </det>
      <det nItem="41">
        <prod>
          <cProd>47426</cProd>
          <cEAN>7891150071087</cEAN>
          <xProd>Amac. Fofo Azul Trad</xProd>
          <NCM>38099190</NCM>
          <CEST>1100800</CEST>
          <CFOP>5405</CFOP>
          <uCom>UN</uCom>
          <qCom>1.0000</qCom>
          <vUnCom>10.5300000000</vUnCom>
          <vProd>10.53</vProd>
          <cEANTrib>7891150071087</cEANTrib>
          <uTrib>UN</uTrib>
          <qTrib>1.0000</qTrib>
          <vUnTrib>10.5300000000</vUnTrib>
          <indTot>1</indTot>
        </prod>
        <imposto>
          <vTotTrib>0.00</vTotTrib>
          <ICMS>
            <ICMS60>
              <orig>0</orig>
              <CST>60</CST>
              <pRedBCEfet>0.00</pRedBCEfet>
              <vBCEfet>10.53</vBCEfet>
              <pICMSEfet>0.00</pICMSEfet>
              <vICMSEfet>0.00</vICMSEfet>
            </ICMS60>
          </ICMS>
          <PIS>
            <PISAliq>
              <CST>01</CST>
              <vBC>10.53</vBC>
              <pPIS>1.65</pPIS>
              <vPIS>0.17</vPIS>
            </PISAliq>
          </PIS>
          <COFINS>
            <COFINSAliq>
              <CST>01</CST>
              <vBC>10.53</vBC>
              <pCOFINS>7.60</pCOFINS>
              <vCOFINS>0.80</vCOFINS>
            </COFINSAliq>
          </COFINS>
        </imposto>
      </det>
      <total>
        <ICMSTot>
          <vBC>30.62</vBC>
          <vICMS>5.34</vICMS>
          <vICMSDeson>4.28</vICMSDeson>
          <vFCP>0.00</vFCP>
          <vBCST>0</vBCST>
          <vST>0.00</vST>
          <vFCPST>0</vFCPST>
          <vFCPSTRet>0</vFCPSTRet>
          <vProd>304.49</vProd>
          <vFrete>0.00</vFrete>
          <vSeg>0</vSeg>
          <vDesc>0.00</vDesc>
          <vII>0</vII>
          <vIPI>0</vIPI>
          <vIPIDevol>0</vIPIDevol>
          <vPIS>1.49</vPIS>
          <vCOFINS>6.88</vCOFINS>
          <vOutro>0.00</vOutro>
          <vNF>304.49</vNF>
          <vTotTrib>0.00</vTotTrib>
        </ICMSTot>
      </total>
      <transp>
        <modFrete>9</modFrete>
      </transp>
      <pag>
        <detPag>
          <indPag>1</indPag>
          <tPag>03</tPag>
          <vPag>304.49</vPag>
          <card>
            <tpIntegra>1</tpIntegra>
            <CNPJ>48407071521000</CNPJ>
            <tBand>02</tBand>
            <cAut>209725</cAut>
          </card>
        </detPag>
        <vTroco>0.00</vTroco>
      </pag>
      <infRespTec>
        <CNPJ>46402051452208</CNPJ>
        <xContato>xContato</xContato>
        <email>email</email>
        <fone>fone</fone>
      </infRespTec>
    </infNFe>
  </NFe>
  <protNFe xmlns="http://www.portalfiscal.inf.br/nfe" versao="4.00">
    <infProt>
      <tpAmb>1</tpAmb>
      <verAplic>SVRSnfce202111190951</verAplic>
      <chNFe>33607102110230600010107517765640727607020031</chNFe>
      <dhRecbto>2022-01-09T10:40:55-03:00</dhRecbto>
      <digVal>digVal</digVal>
      <cStat>cStat</cStat>
      <xMotivo>Autorizado o uso da NF-e</xMotivo>
    </infProt>
  </protNFe>
</nfeProc>
